azurefunctions/extensions/mcp/__init__.py
azurefunctions/extensions/mcp/constants.py
azurefunctions/extensions/mcp/utils.py
azurefunctions/extensions/mcp/decorators/__init__.py
azurefunctions/extensions/mcp/decorators/mcp.py
azurefunctions/extensions/mcp/decorators/mcp_app.py
func_mcp_test-0.0.0a1.dist-info/licenses/LICENSE
func_mcp_test-0.0.0a1.dist-info/METADATA
func_mcp_test-0.0.0a1.dist-info/WHEEL
func_mcp_test-0.0.0a1.dist-info/top_level.txt
func_mcp_test-0.0.0a1.dist-info/RECORD
