Metadata-Version: 2.4
Name: func-mcp-test
Version: 0.0.0a1
Summary: MCP Python worker extension for Azure Functions.
Author-email: "Azure Functions team at Microsoft Corp." <azurefunctions@microsoft.com>
License: MIT License
Classifier: License :: OSI Approved :: MIT License
Classifier: Intended Audience :: Developers
Classifier: Programming Language :: Python :: 3
Classifier: Programming Language :: Python :: 3.10
Classifier: Programming Language :: Python :: 3.11
Classifier: Programming Language :: Python :: 3.12
Classifier: Programming Language :: Python :: 3.13
Classifier: Operating System :: Microsoft :: Windows
Classifier: Operating System :: POSIX
Classifier: Operating System :: MacOS :: MacOS X
Classifier: Environment :: Web Environment
Classifier: Development Status :: 5 - Production/Stable
Requires-Python: >=3.10
License-File: LICENSE
Requires-Dist: azure-functions>=1.24.0
Provides-Extra: dev
Requires-Dist: flake8; extra == "dev"
Requires-Dist: mypy; extra == "dev"
Requires-Dist: pytest; extra == "dev"
Requires-Dist: pytest-cov; extra == "dev"
Requires-Dist: coverage; extra == "dev"
Requires-Dist: pytest-instafail; extra == "dev"
Requires-Dist: pre-commit; extra == "dev"
Dynamic: license-file
